__init__.py
dodolib/__init__.py
dodolib/models/__init__.py
dodolib/models/aliases.py
dodolib/models/auth.py
dodolib/models/database.py
dodolib/models/dodo_api.py
dodolib/services/__init__.py
dodolib/services/auth_credentials.py
dodolib/services/base.py
dodolib/services/db_api.py
dodolib/services/dodo_api.py
dodolib/utils/__init__.py
dodolib/utils/convert_models.py
dodolib/utils/env_vars.py
dodolib/utils/exceptions.py
dodolib/utils/logger.py
dodo_lib_usbtypec1-1.5.2.dist-info/LICENSE
dodo_lib_usbtypec1-1.5.2.dist-info/METADATA
dodo_lib_usbtypec1-1.5.2.dist-info/WHEEL
dodo_lib_usbtypec1-1.5.2.dist-info/top_level.txt
dodo_lib_usbtypec1-1.5.2.dist-info/RECORD
