Metadata-Version: 2.1
Name: dodo-lib-usbtypec1
Version: 1.5.2
Summary: Wrapper on dodo api and dodo database
Author-email: Eldos <eldos.baktybekov@gmail.com>
License: MIT License
Classifier: Programming Language :: Python :: 3
Classifier: License :: OSI Approved :: MIT License
Classifier: Operating System :: OS Independent
Requires-Python: >=3.10
License-File: LICENSE
Requires-Dist: httpx (~=0.23.0)
Requires-Dist: pydantic (~=1.9.1)
Requires-Dist: python-dotenv (~=0.20.0)
